calc_pck/.DS_Store
calc_pck/__init__.py
calc_pck/patcalc.py
calc_pck-0.1.1.dist-info/LICENSE
calc_pck-0.1.1.dist-info/WHEEL
calc_pck-0.1.1.dist-info/METADATA
calc_pck-0.1.1.dist-info/RECORD
