Metadata-Version: 2.1
Name: calc_pck
Version: 0.1.1
Summary: Basic arithmetics calculator
Author-email: Patricia Osorio <patosorio.88@gmail.com>
Classifier: License :: OSI Approved :: MIT License
